{"nodes": [{"id": "github_pull_request_template_md", "label": "pull_request_template.md", "file_type": "document", "source_file": ".github/pull_request_template.md", "source_location": "L1"}, {"id": "github_pull_request_template_linked_issue", "label": "Linked issue", "file_type": "document", "source_file": ".github/pull_request_template.md", "source_location": "L4"}, {"id": "github_pull_request_template_why_this_change", "label": "Why this change", "file_type": "document", "source_file": ".github/pull_request_template.md", "source_location": "L10"}, {"id": "github_pull_request_template_what_changed", "label": "What changed", "file_type": "document", "source_file": ".github/pull_request_template.md", "source_location": "L16"}, {"id": "github_pull_request_template_refactor_impact", "label": "Refactor impact", "file_type": "document", "source_file": ".github/pull_request_template.md", "source_location": "L22"}, {"id": "github_pull_request_template_validation", "label": "Validation", "file_type": "document", "source_file": ".github/pull_request_template.md", "source_location": "L44"}, {"id": "github_pull_request_template_manual_verification_notes", "label": "Manual verification notes", "file_type": "document", "source_file": ".github/pull_request_template.md", "source_location": "L59"}, {"id": "github_pull_request_template_docs_and_release_impact", "label": "Docs and release impact", "file_type": "document", "source_file": ".github/pull_request_template.md", "source_location": "L65"}, {"id": "github_pull_request_template_ui_evidence", "label": "UI evidence", "file_type": "document", "source_file": ".github/pull_request_template.md", "source_location": "L74"}], "edges": [{"source": "github_pull_request_template_md", "target": "github_pull_request_template_linked_issue", "relation": "contains", "confidence": "EXTRACTED", "source_file": ".github/pull_request_template.md", "source_location": "L4", "weight": 1.0}, {"source": "github_pull_request_template_md", "target": "github_pull_request_template_why_this_change", "relation": "contains", "confidence": "EXTRACTED", "source_file": ".github/pull_request_template.md", "source_location": "L10", "weight": 1.0}, {"source": "github_pull_request_template_md", "target": "github_pull_request_template_what_changed", "relation": "contains", "confidence": "EXTRACTED", "source_file": ".github/pull_request_template.md", "source_location": "L16", "weight": 1.0}, {"source": "github_pull_request_template_md", "target": "github_pull_request_template_refactor_impact", "relation": "contains", "confidence": "EXTRACTED", "source_file": ".github/pull_request_template.md", "source_location": "L22", "weight": 1.0}, {"source": "github_pull_request_template_md", "target": "github_pull_request_template_validation", "relation": "contains", "confidence": "EXTRACTED", "source_file": ".github/pull_request_template.md", "source_location": "L44", "weight": 1.0}, {"source": "github_pull_request_template_validation", "target": "github_pull_request_template_manual_verification_notes", "relation": "contains", "confidence": "EXTRACTED", "source_file": ".github/pull_request_template.md", "source_location": "L59", "weight": 1.0}, {"source": "github_pull_request_template_md", "target": "github_pull_request_template_docs_and_release_impact", "relation": "contains", "confidence": "EXTRACTED", "source_file": ".github/pull_request_template.md", "source_location": "L65", "weight": 1.0}, {"source": "github_pull_request_template_md", "target": "github_pull_request_template_ui_evidence", "relation": "contains", "confidence": "EXTRACTED", "source_file": ".github/pull_request_template.md", "source_location": "L74", "weight": 1.0}], "input_tokens": 0, "output_tokens": 0}